AlgebraTopologyDifferentialCalculusAndOptimizationTheoryForComputerScienceAndEngineering/README.md
AlgebraTopologyDifferentialCalculusAndOptimizationTheoryForComputerScienceAndEngineering/__init__.py
AlgebraTopologyDifferentialCalculusAndOptimizationTheoryForComputerScienceAndEngineering/__main__.py
AlgebraTopologyDifferentialCalculusAndOptimizationTheoryForComputerScienceAndEngineering/file.pdf
AlgebraTopologyDifferentialCalculusAndOptimizationTheoryForComputerScienceAndEngineering/index.html
algebra_topology_differential_calculus_and_optimization_theory_for_computer_science_and_engineering-2024.3.4.0.dist-info/METADATA
algebra_topology_differential_calculus_and_optimization_theory_for_computer_science_and_engineering-2024.3.4.0.dist-info/WHEEL
algebra_topology_differential_calculus_and_optimization_theory_for_computer_science_and_engineering-2024.3.4.0.dist-info/entry_points.txt
algebra_topology_differential_calculus_and_optimization_theory_for_computer_science_and_engineering-2024.3.4.0.dist-info/top_level.txt
algebra_topology_differential_calculus_and_optimization_theory_for_computer_science_and_engineering-2024.3.4.0.dist-info/RECORD
