Metadata-Version: 2.1
Name: algebra-topology-differential-calculus-and-optimization-theory-for-computer-science-and-engineering
Version: 2024.3.4.0
Summary: Algebra, Topology, Differential Calculus, and Optimization Theory For Computer Science and Engineering
Home-page: https://github.com/apachecn/algebra-topology-differential-calculus-and-optimization-theory-for-computer-science-and-engineering
Author: ApacheCN
Author-email: apachecn@163.com
Classifier: Development Status :: 4 - Beta
Classifier: Environment :: Console
Classifier: Intended Audience :: Developers
Classifier: Intended Audience :: End Users/Desktop
Classifier: License :: Other/Proprietary License
Classifier: Natural Language :: Chinese (Simplified)
Classifier: Natural Language :: English
Classifier: Operating System :: OS Independent
Classifier: Programming Language :: Python :: 3
Classifier: Programming Language :: Python :: 3 :: Only
Classifier: Programming Language :: Python :: 3.6
Classifier: Programming Language :: Python :: 3.7
Classifier: Topic :: Text Processing :: Markup :: Markdown
Classifier: Topic :: Text Processing :: Markup :: HTML
Classifier: Topic :: Internet :: WWW/HTTP
Classifier: Topic :: Software Development :: Documentation
Classifier: Topic :: Documentation
Requires-Python: >=3.6
